pywen/__init__.py
pywen/main.py
pywen/agents/__init__.py
pywen/agents/agent_events.py
pywen/agents/agent_manager.py
pywen/agents/base_agent.py
pywen/agents/claude/__init__.py
pywen/agents/claude/claude_agent.py
pywen/agents/claude/context_manager.py
pywen/agents/claude/prompts.py
pywen/agents/claude/system_reminder.py
pywen/agents/codex/codex_agent.py
pywen/agents/codex/gpt_5_codex_prompt.md
pywen/agents/codex/prompt.md
pywen/agents/pywen/__init__.py
pywen/agents/pywen/pywen_agent.py
pywen/agents/research/google_research_agent.py
pywen/agents/research/research_prompts.py
pywen/cli/__init__.py
pywen/cli/cli_console.py
pywen/cli/command_processor.py
pywen/cli/diff_display.py
pywen/cli/highlighted_content.py
pywen/cli/runtime.py
pywen/cli/commands/__init__.py
pywen/cli/commands/about_command.py
pywen/cli/commands/agent_command.py
pywen/cli/commands/base_command.py
pywen/cli/commands/bug_command.py
pywen/cli/commands/clear_command.py
pywen/cli/commands/help_command.py
pywen/cli/commands/memory_command.py
pywen/cli/commands/model_command.py
pywen/cli/commands/placeholder_commands.py
pywen/cli/commands/quit_command.py
pywen/cli/commands/stats_command.py
pywen/cli/commands/tools_command.py
pywen/config/__init__.py
pywen/config/config.py
pywen/config/manager.py
pywen/config/pywen_config.example.yaml
pywen/config/token_limits.py
pywen/hooks/README.md
pywen/hooks/__init__.py
pywen/hooks/config.py
pywen/hooks/integrate.py
pywen/hooks/manager.py
pywen/hooks/matcher.py
pywen/hooks/middleware.py
pywen/hooks/models.py
pywen/hooks/runner.py
pywen/llm/llm_basics.py
pywen/llm/llm_client.py
pywen/llm/llm_events.py
pywen/llm/adapters/__init__.py
pywen/llm/adapters/anthropic_adapter.py
pywen/llm/adapters/openai_adapter.py
pywen/memory/file_restorer.py
pywen/memory/memory_monitor.py
pywen/memory/prompt.py
pywen/tools/apply_patch_tool.py
pywen/tools/base_tool.py
pywen/tools/bash_tool.py
pywen/tools/codex_shell_tool.py
pywen/tools/edit_tool.py
pywen/tools/file_tools.py
pywen-2.0.0.dist-info/METADATA
pywen-2.0.0.dist-info/WHEEL
pywen-2.0.0.dist-info/entry_points.txt
pywen-2.0.0.dist-info/licenses/LICENSE
pywen-2.0.0.dist-info/RECORD
