Metadata-Version: 2.4
Name: pywen
Version: 2.0.0
Summary: LLM-based agent for general purpose tasks
Author: PAMPAS-Lab, LI YAO
Author-email: CHEN LONGRONG <longrongchen@163.com>, XUE YIBO <yiboxue@163.com>
License: MIT
License-File: LICENSE
Keywords: agent,cli,llm
Classifier: License :: OSI Approved :: MIT License
Classifier: Operating System :: OS Independent
Classifier: Programming Language :: Python :: 3
Requires-Python: <3.13,>=3.10
Requires-Dist: aiohttp>=3.12.13
Requires-Dist: anthropic>=0.54.0
Requires-Dist: click>=8.0.0
Requires-Dist: google-genai>=1.24.0
Requires-Dist: jsonpath-ng>=1.7.0
Requires-Dist: keyboard>=0.13.5
Requires-Dist: loguru>=0.7.3
Requires-Dist: mcp>=1.13.0
Requires-Dist: ollama>=0.5.1
Requires-Dist: openai>=2.6.0
Requires-Dist: prompt-toolkit>=3.0.51
Requires-Dist: pydantic>=2.0.0
Requires-Dist: pytest>=8.0.0
Requires-Dist: python-dotenv>=1.0.0
Requires-Dist: pyyaml>=6.0
Requires-Dist: rich>=13.0.0
Requires-Dist: ruff>=0.12.4
Requires-Dist: socksio>=1.0.0
Requires-Dist: textual>=5.0.1
Requires-Dist: tree-sitter-languages==1.10.2
Requires-Dist: tree-sitter==0.21.3
Requires-Dist: typing-extensions>=4.0.0
Provides-Extra: evaluation
Requires-Dist: datasets>=2.14.0; extra == 'evaluation'
Requires-Dist: docker>=7.0.0; extra == 'evaluation'
Requires-Dist: sb-cli>=0.1.4; extra == 'evaluation'
Requires-Dist: tqdm>=4.66.0; extra == 'evaluation'
